README.md
setup.py
sbc/__init__.py
sbc/sbc.py
sbc.egg-info/PKG-INFO
sbc.egg-info/SOURCES.txt
sbc.egg-info/dependency_links.txt
sbc.egg-info/top_level.txt