Metadata-Version: 2.1
Name: sbc
Version: 1.3
Summary: struct convert binary
Home-page: https://github.com/jdhxyy/sbc-python
Author: jdh99
Author-email: jdh821@163.com
License: UNKNOWN
Platform: UNKNOWN
